{"trial_id": "0023", "hyperparameters": {"space": [{"class_name": "Choice", "config": {"name": "activation", "default": "relu", "conditions": [], "values": ["relu", "tanh", "sigmoid"], "ordered": false}}, {"class_name": "Int", "config": {"name": "time_units1", "default": null, "conditions": [], "min_value": 32, "max_value": 512, "step": 1, "sampling": "linear"}}, {"class_name": "Int", "config": {"name": "time_units2", "default": null, "conditions": [], "min_value": 32, "max_value": 512, "step": 1, "sampling": "linear"}}, {"class_name": "Int", "config": {"name": "time_units3", "default": null, "conditions": [], "min_value": 16, "max_value": 256, "step": 1, "sampling": "linear"}}, {"class_name": "Int", "config": {"name": "time_units4", "default": null, "conditions": [], "min_value": 4, "max_value": 128, "step": 1, "sampling": "linear"}}, {"class_name": "Int", "config": {"name": "temp_units1", "default": null, "conditions": [], "min_value": 32, "max_value": 256, "step": 1, "sampling": "linear"}}, {"class_name": "Int", "config": {"name": "temp_units2", "default": null, "conditions": [], "min_value": 32, "max_value": 128, "step": 1, "sampling": "linear"}}, {"class_name": "Int", "config": {"name": "temp_units3", "default": null, "conditions": [], "min_value": 4, "max_value": 32, "step": 1, "sampling": "linear"}}], "values": {"activation": "tanh", "time_units1": 314, "time_units2": 106, "time_units3": 42, "time_units4": 91, "temp_units1": 112, "temp_units2": 54, "temp_units3": 6, "tuner/epochs": 20, "tuner/initial_epoch": 0, "tuner/bracket": 0, "tuner/round": 0}}, "metrics": {"metrics": {"TTemp_out_accuracy": {"direction": "min", "observations": [{"value": [0.30041494965553284], "step": 19}]}, "TTemp_out_loss": {"direction": "min", "observations": [{"value": [1.8823392152786256], "step": 19}]}, "TTime_out_accuracy": {"direction": "min", "observations": [{"value": [0.35103734731674197], "step": 19}]}, "TTime_out_loss": {"direction": "min", "observations": [{"value": [1.435218048095703], "step": 19}]}, "loss": {"direction": "min", "observations": [{"value": [3.3204489231109617], "step": 19}]}, "val_TTemp_out_accuracy": {"direction": "min", "observations": [{"value": [0.27204968631267545], "step": 19}]}, "val_TTemp_out_loss": {"direction": "min", "observations": [{"value": [1.9065629482269286], "step": 19}]}, "val_TTime_out_accuracy": {"direction": "min", "observations": [{"value": [0.2782608687877655], "step": 19}]}, "val_TTime_out_loss": {"direction": "min", "observations": [{"value": [1.5210697174072265], "step": 19}]}, "val_loss": {"direction": "min", "observations": [{"value": [3.437566328048706], "step": 19}]}, "multi_objective": {"direction": "min", "observations": [{"value": [3.437566328048706], "step": 19}]}}}, "score": 3.437566328048706, "best_step": 19, "status": "COMPLETED", "message": null}